{
"skeleton": { "hash": "QyK41ESNTzCtnoN2t5chbni7t1I", "spine": "3.7.87", "width": 2812.27, "height": 500.66, "images": "../../BGs/BG1/", "audio": "D:/GoKids/tbi/tbisland_animations/Spine/BGs" },
"bones": [
	{ "name": "root", "scaleX": 0.5, "scaleY": 0.5 },
	{ "name": "bone2", "parent": "root", "x": 115.51, "y": -140.27 },
	{ "name": "bone", "parent": "bone2", "x": -115.51, "y": -39.73 },
	{ "name": "bone4", "parent": "bone2", "length": 3085.23, "rotation": -0.06, "x": -1645.26, "y": -654.61 },
	{ "name": "bone5", "parent": "bone2", "length": 118.59, "rotation": 0.74, "x": -1525.94, "y": -287.18 },
	{ "name": "bone6", "parent": "bone5", "length": 128.59, "rotation": -0.74, "x": 118.59 },
	{ "name": "bone7", "parent": "bone6" },
	{ "name": "bone8", "parent": "bone7", "length": 120.89, "rotation": 0.36, "x": 128.59 },
	{ "name": "bone9", "parent": "bone8", "length": 121.66, "x": 120.89 },
	{ "name": "bone10", "parent": "bone9", "length": 123.21, "rotation": 0.35, "x": 120.28, "y": -0.51 },
	{ "name": "bone11", "parent": "bone10", "length": 103.96, "rotation": -1.56, "x": 123.21 },
	{ "name": "bone12", "parent": "bone11", "length": 121.66, "rotation": 0.85, "x": 103.96 },
	{ "name": "bone13", "parent": "bone12", "length": 125.51, "rotation": -0.35, "x": 121.66 },
	{ "name": "bone14", "parent": "bone13", "length": 118.58, "rotation": 0.72, "x": 127.96, "y": 0.19 },
	{ "name": "bone15", "parent": "bone14", "length": 126.29, "rotation": 0.33, "x": 118.58 },
	{ "name": "bone16", "parent": "bone15", "length": 137.84, "rotation": -0.06, "x": 127.51, "y": -1.56 },
	{ "name": "bone17", "parent": "bone16", "length": 111.65, "rotation": -0.64, "x": 137.84 },
	{ "name": "bone18", "parent": "bone17", "length": 128.6, "rotation": 0.69, "x": 113.18, "y": -2.31 },
	{ "name": "bone19", "parent": "bone18", "length": 106.28, "rotation": -1.93, "x": 128.6 },
	{ "name": "bone20", "parent": "bone19", "length": 103.96, "rotation": 0.4, "x": 102.19, "y": 1.45 },
	{ "name": "bone21", "parent": "bone20", "length": 117.04, "rotation": 0.85, "x": 103.96 },
	{ "name": "bone22", "parent": "bone21", "length": 124.74, "rotation": 0.35, "x": 117.04 },
	{ "name": "bone23", "parent": "bone22", "length": 140.94, "rotation": 0.9, "x": 126.64, "y": -1.55 },
	{ "name": "bone24", "parent": "bone23", "length": 111.72, "rotation": -3.23, "x": 140.94 },
	{ "name": "bone25", "parent": "bone24", "length": 143.22, "rotation": 2.28, "x": 111.71, "y": 0.77 },
	{ "name": "bone26", "parent": "bone25", "length": 157.87, "rotation": -1.15, "x": 143.22 },
	{ "name": "bone27", "parent": "bone26", "length": 133.98, "rotation": 0.84, "x": 156.33, "y": -0.02 },
	{ "name": "bone28", "parent": "bone27", "length": 109.38, "rotation": 1.61, "x": 133.52, "y": 0.69 }
],
"slots": [
	{ "name": "Waterline", "bone": "bone", "attachment": "Waterline" },
	{ "name": "water", "bone": "bone2", "attachment": "water" }
],
"path": [
	{
		"name": "water1",
		"order": 0,
		"bones": [ "bone5", "bone6", "bone8", "bone9", "bone10", "bone11", "bone12", "bone13", "bone14", "bone15", "bone16", "bone17", "bone18", "bone19", "bone20", "bone21", "bone22", "bone23", "bone24", "bone25", "bone26", "bone27", "bone28" ],
		"target": "water",
		"spacingMode": "percent",
		"rotateMode": "chainScale",
		"spacing": 0.0435
	}
],
"skins": {
	"default": {
		"Waterline": {
			"Waterline": {
				"type": "mesh",
				"uvs": [ 1, 1, 0.98959, 1, 0.97439, 1, 0.95751, 1, 0.94513, 1, 0.92768, 1, 0.9153, 1, 0.89786, 1, 0.88942, 1, 0.87591, 1, 0.86353, 1, 0.84833, 1, 0.82695, 1, 0.80894, 1, 0.79262, 1, 0.77461, 1, 0.75782, 1, 0.746, 1, 0.72968, 1, 0.70943, 1, 0.69367, 1, 0.67678, 1, 0.66215, 1, 0.64527, 1, 0.63021, 1, 0.61558, 1, 0.60095, 1, 0.58294, 1, 0.56662, 1, 0.54805, 1, 0.52948, 1, 0.51203, 1, 0.4974, 1, 0.48305, 1, 0.46729, 1, 0.44984, 1, 0.43296, 1, 0.41326, 1, 0.39132, 1, 0.37383, 1, 0.35357, 1, 0.33106, 1, 0.31699, 1, 0.29898, 1, 0.28041, 1, 0.25903, 1, 0.24158, 1, 0.21513, 1, 0.19318, 1, 0.17799, 1, 0.16336, 1, 0.14591, 1, 0.12678, 1, 0.10595, 1, 0.09132, 1, 0.07219, 1, 0.05418, 1, 0.03898, 1, 0.0221, 1, 0.01197, 1, 0, 1, 0, 0, 0.01424, 0, 0.03325, 0, 0.04874, 0, 0.06634, 0, 0.08816, 0, 0.10154, 0, 0.11843, 0, 0.13815, 0, 0.14651, 0, 0.15504, 0, 0.16428, 0, 0.17194, 0, 0.18205, 0, 0.19095, 0, 0.19878, 0, 0.20714, 0, 0.21629, 0, 0.22614, 0, 0.23303, 0, 0.24163, 0, 0.25208, 0, 0.26346, 0, 0.27329, 0, 0.28111, 0, 0.29208, 0, 0.2988, 0, 0.31007, 0, 0.31849, 0, 0.32887, 0, 0.33707, 0, 0.34509, 0, 0.35282, 0, 0.35934, 0, 0.36633, 0, 0.37839, 0, 0.38434, 0, 0.39024, 0, 0.39897, 0, 0.40594, 0, 0.41304, 0, 0.42161, 0, 0.43161, 0, 0.43912, 0, 0.44455, 0, 0.45148, 0, 0.45919, 0, 0.46769, 0, 0.47551, 0, 0.48289, 0, 0.49014, 0, 0.49756, 0, 0.50646, 0, 0.51427, 0, 0.52165, 0, 0.52998, 0, 0.53772, 0, 0.54646, 0, 0.5563, 0, 0.56268, 0, 0.5698, 0, 0.58076, 0, 0.5895, 0, 0.59827, 0, 0.60751, 0, 0.61707, 0, 0.62552, 0, 0.63406, 0, 0.64465, 0, 0.65473, 0, 0.66322, 0, 0.67121, 0, 0.67577, 0, 0.68254, 0, 0.69097, 0, 0.69995, 0, 0.70954, 0, 0.71668, 0, 0.72361, 0, 0.73085, 0, 0.74049, 0, 0.7504, 0, 0.75753, 0, 0.76636, 0, 0.77272, 0, 0.78284, 0, 0.79354, 0, 0.80172, 0, 0.80705, 0, 0.81717, 0, 0.82618, 0, 0.83751, 0, 0.85038, 0, 0.86051, 0, 0.86779, 0, 0.87571, 0, 0.88921, 0, 0.90947, 0, 0.92354, 0, 0.93592, 0, 0.95618, 0, 0.96913, 0, 0.98376, 0, 1, 0 ],
				"triangles": [ 62, 59, 61, 58, 62, 63, 56, 64, 65, 54, 66, 67, 53, 67, 68, 52, 68, 69, 51, 69, 70, 50, 71, 72, 51, 70, 71, 50, 72, 73, 49, 73, 74, 48, 75, 76, 74, 75, 48, 47, 77, 78, 48, 76, 77, 46, 80, 81, 79, 80, 46, 47, 78, 79, 46, 81, 82, 45, 82, 83, 44, 84, 85, 45, 83, 84, 44, 85, 86, 43, 87, 88, 86, 87, 43, 42, 88, 89, 41, 90, 91, 42, 89, 90, 40, 93, 94, 92, 93, 40, 41, 91, 92, 39, 95, 96, 40, 94, 95, 39, 96, 97, 38, 98, 99, 97, 98, 38, 37, 101, 102, 100, 101, 37, 99, 100, 37, 102, 103, 36, 36, 103, 104, 35, 105, 106, 104, 105, 35, 34, 107, 108, 35, 106, 107, 34, 108, 109, 33, 110, 111, 109, 110, 33, 32, 111, 112, 31, 113, 114, 32, 112, 113, 31, 114, 115, 29, 118, 119, 117, 118, 29, 30, 116, 117, 119, 120, 28, 28, 120, 121, 27, 122, 123, 121, 122, 27, 26, 124, 125, 25, 125, 126, 24, 127, 128, 25, 126, 127, 23, 129, 130, 128, 129, 23, 22, 130, 131, 132, 133, 21, 22, 131, 132, 21, 133, 134, 20, 135, 136, 134, 135, 20, 19, 136, 137, 138, 139, 18, 19, 137, 138, 18, 139, 140, 17, 141, 142, 18, 140, 141, 16, 143, 144, 142, 143, 16, 144, 145, 15, 15, 145, 146, 14, 146, 147, 13, 149, 150, 148, 149, 13, 14, 147, 148, 12, 151, 152, 150, 151, 12, 11, 152, 153, 10, 154, 155, 11, 153, 154, 9, 156, 157, 155, 156, 9, 158, 7, 157, 6, 158, 159, 5, 159, 160, 4, 160, 161, 3, 161, 162, 59, 60, 61, 59, 62, 58, 57, 63, 64, 58, 63, 57, 57, 64, 56, 56, 65, 55, 55, 66, 54, 54, 67, 53, 53, 68, 52, 52, 69, 51, 50, 51, 71, 49, 50, 73, 49, 74, 48, 47, 48, 77, 46, 47, 79, 45, 46, 82, 44, 45, 84, 43, 44, 86, 43, 88, 42, 41, 42, 90, 40, 41, 92, 39, 40, 95, 38, 39, 97, 38, 99, 37, 37, 102, 36, 36, 104, 35, 34, 35, 107, 33, 34, 109, 33, 111, 32, 31, 32, 113, 30, 31, 115, 29, 30, 117, 29, 119, 28, 28, 121, 27, 123, 124, 26, 27, 123, 26, 26, 125, 25, 24, 25, 127, 24, 128, 23, 23, 130, 22, 21, 22, 132, 21, 134, 20, 20, 136, 19, 18, 19, 138, 17, 18, 141, 17, 142, 16, 16, 144, 15, 15, 146, 14, 13, 14, 148, 13, 150, 12, 12, 152, 11, 10, 11, 154, 10, 155, 9, 7, 8, 157, 9, 157, 8, 7, 158, 6, 6, 159, 5, 5, 160, 4, 4, 161, 3, 55, 65, 66, 30, 115, 116, 2, 162, 163, 3, 162, 2, 1, 163, 164, 0, 1, 164, 2, 163, 1 ],
				"vertices": [ 3, 3, 2931.85, -105.2, 0.62963, 27, 73.87, -479.02, 0.35257, 26, 220.84, -476.07, 0.0178, 3, 3, 2902.66, -105.23, 0.85185, 27, 44.68, -478.2, 0.14814, 26, 191.65, -476.07, 1.0E-5, 3, 3, 2860.05, -105.27, 0.96296, 27, 2.1, -477, 0.03703, 26, 149.04, -476.07, 0, 1, 3, 2812.71, -105.32, 1, 1, 3, 2778, -105.35, 1, 1, 3, 2729.08, -105.4, 1, 1, 3, 2694.36, -105.44, 1, 1, 3, 2645.45, -105.48, 1, 1, 3, 2621.78, -105.51, 1, 1, 3, 2583.9, -105.55, 1, 1, 3, 2549.19, -105.58, 1, 1, 3, 2506.58, -105.62, 1, 1, 3, 2446.62, -105.68, 1, 1, 3, 2396.12, -105.73, 1, 1, 3, 2350.36, -105.78, 1, 1, 3, 2299.86, -105.83, 1, 1, 3, 2252.79, -105.88, 1, 1, 3, 2219.65, -105.91, 1, 1, 3, 2173.89, -105.95, 1, 1, 3, 2117.08, -106.01, 1, 1, 3, 2072.9, -106.06, 1, 1, 3, 2025.56, -106.1, 1, 1, 3, 1984.53, -106.14, 1, 1, 3, 1937.19, -106.19, 1, 1, 3, 1894.97, -106.23, 1, 1, 3, 1853.94, -106.27, 1, 1, 3, 1812.91, -106.31, 1, 1, 3, 1762.42, -106.36, 1, 1, 3, 1716.65, -106.41, 1, 1, 3, 1664.58, -106.46, 1, 1, 3, 1612.51, -106.51, 1, 1, 3, 1563.59, -106.56, 1, 1, 3, 1522.56, -106.6, 1, 1, 3, 1482.32, -106.64, 1, 1, 3, 1438.13, -106.69, 1, 1, 3, 1389.22, -106.74, 1, 1, 3, 1341.88, -106.78, 1, 1, 3, 1286.65, -106.84, 1, 1, 3, 1225.1, -106.9, 1, 1, 3, 1176.08, -106.95, 1, 1, 3, 1119.27, -107.01, 1, 1, 3, 1056.15, -107.07, 1, 1, 3, 1016.7, -107.11, 1, 1, 3, 966.2, -107.16, 1, 1, 3, 914.13, -107.21, 1, 1, 3, 854.16, -107.27, 1, 1, 3, 805.25, -107.32, 1, 1, 3, 731.08, -107.39, 1, 1, 3, 669.54, -107.45, 1, 1, 3, 626.93, -107.5, 1, 1, 3, 585.9, -107.54, 1, 1, 3, 536.99, -107.59, 1, 3, 3, 483.33, -107.64, 1, 5, 246.49, -478.71, 0, 4, 358.85, -481.88, 0, 3, 3, 424.95, -107.7, 1, 5, 188.11, -478.71, 0, 4, 300.47, -481.12, 0, 3, 3, 383.92, -107.74, 0.99999, 5, 147.08, -478.71, 0, 4, 259.44, -480.58, 1.0E-5, 3, 3, 330.27, -107.79, 0.99994, 5, 93.43, -478.71, 2.0E-5, 4, 205.79, -479.89, 4.0E-5, 3, 3, 279.77, -107.84, 0.99984, 5, 42.93, -478.71, 4.0E-5, 4, 155.3, -479.23, 1.1E-4, 3, 3, 237.17, -107.89, 0.99967, 5, 0.33, -478.71, 9.0E-5, 4, 112.7, -478.68, 2.4E-4, 3, 3, 189.83, -107.93, 0.96245, 5, -47.01, -478.71, 1.5E-4, 4, 65.36, -478.06, 0.0374, 3, 3, 161.42, -107.96, 0.85125, 5, -75.42, -478.71, 1.9E-4, 4, 36.96, -477.7, 0.14857, 3, 3, 127.85, -107.99, 0.6291, 5, -108.99, -478.71, 0.00135, 4, 3.4, -477.26, 0.36955, 3, 3, 127.36, 384.01, 0.37002, 5, -108.99, 13.29, 0.04068, 4, 9.79, 14.7, 0.58929, 3, 3, 167.3, 384.05, 0.148, 5, -69.05, 13.29, 0.15524, 4, 49.72, 14.18, 0.69676, 4, 3, 220.6, 384.1, 0.037, 7, -144.25, 14.2, 0.02984, 5, -15.75, 13.29, 0.34874, 4, 103.01, 13.49, 0.58442, 3, 7, -100.83, 13.93, 0.12655, 5, 27.68, 13.29, 0.51009, 4, 146.44, 12.92, 0.36335, 3, 7, -51.48, 13.61, 0.32718, 5, 77.03, 13.29, 0.52818, 4, 195.78, 12.28, 0.14464, 4, 8, -111.18, 13.22, 0.03704, 7, 9.71, 13.22, 0.54221, 5, 138.22, 13.29, 0.38489, 4, 256.97, 11.49, 0.03587, 3, 8, -73.67, 12.98, 0.14815, 7, 47.22, 12.98, 0.66051, 5, 175.73, 13.29, 0.19134, 3, 8, -26.3, 12.68, 0.37037, 7, 94.59, 12.68, 0.571, 5, 223.1, 13.29, 0.05863, 3, 8, 28.97, 12.33, 0.62963, 7, 149.87, 12.33, 0.36317, 5, 278.37, 13.29, 0.0072, 3, 9, -67.76, 13.11, 0.0212, 8, 52.43, 12.18, 0.83065, 7, 173.33, 12.18, 0.14815, 3, 9, -43.85, 12.81, 0.10063, 8, 76.35, 12.03, 0.86233, 7, 197.24, 12.03, 0.03704, 2, 9, -17.95, 12.49, 0.27534, 8, 102.25, 11.87, 0.72466, 2, 9, 3.52, 12.22, 0.51876, 8, 123.72, 11.73, 0.48124, 2, 9, 31.86, 11.86, 0.75682, 8, 152.07, 11.55, 0.24318, 3, 10, -66.68, 9.74, 0.02391, 9, 56.82, 11.55, 0.89154, 8, 177.02, 11.4, 0.08455, 3, 10, -44.71, 10.06, 0.10878, 9, 78.79, 11.28, 0.87539, 8, 199, 11.26, 0.01584, 2, 10, -21.29, 10.41, 0.29163, 9, 102.21, 10.99, 0.70837, 2, 10, 4.38, 10.79, 0.53776, 9, 127.88, 10.66, 0.46224, 3, 11, -71.78, 12.26, 0.01939, 10, 32.01, 11.2, 0.75371, 9, 155.51, 10.32, 0.22689, 3, 11, -52.48, 12.26, 0.09522, 10, 51.31, 11.48, 0.82837, 9, 174.81, 10.08, 0.07641, 3, 11, -28.35, 12.26, 0.26451, 10, 75.43, 11.84, 0.72236, 9, 198.93, 9.78, 0.01312, 2, 11, 0.95, 12.26, 0.50613, 10, 104.73, 12.27, 0.49387, 3, 12, -88.89, 11.72, 0.00884, 11, 32.84, 12.26, 0.73716, 10, 136.62, 12.75, 0.254, 3, 12, -61.33, 11.89, 0.05669, 11, 60.41, 12.26, 0.85335, 10, 164.18, 13.16, 0.08996, 3, 12, -39.4, 12.02, 0.18059, 11, 82.34, 12.26, 0.80176, 10, 186.11, 13.48, 0.01764, 2, 12, -8.62, 12.21, 0.39108, 11, 113.11, 12.26, 0.60892, 2, 12, 10.2, 12.32, 0.63464, 11, 131.94, 12.26, 0.36536, 3, 13, -85.99, 13.41, 0.00884, 12, 41.81, 12.52, 0.82837, 11, 163.54, 12.26, 0.16279, 3, 13, -62.37, 13.26, 0.06181, 12, 65.43, 12.66, 0.88942, 11, 187.17, 12.26, 0.04878, 3, 13, -33.28, 13.07, 0.19593, 12, 94.51, 12.84, 0.79721, 11, 216.25, 12.26, 0.00686, 2, 13, -10.29, 12.92, 0.42172, 12, 117.5, 12.98, 0.57828, 2, 13, 12.2, 12.78, 0.67037, 12, 140, 13.12, 0.32963, 3, 14, -84.62, 13.12, 0.00349, 13, 33.89, 12.63, 0.86433, 12, 161.68, 13.25, 0.13218, 3, 14, -66.35, 12.89, 0.03269, 13, 52.16, 12.52, 0.93383, 12, 179.95, 13.37, 0.03347, 3, 14, -46.75, 12.66, 0.12464, 13, 71.76, 12.39, 0.8736, 12, 199.56, 13.49, 0.00176, 2, 14, -12.93, 12.24, 0.30589, 13, 105.58, 12.17, 0.69411, 2, 14, 3.74, 12.04, 0.54683, 13, 122.25, 12.06, 0.45317, 2, 14, 20.28, 11.84, 0.7734, 13, 138.79, 11.95, 0.2266, 3, 15, -82.76, 13.01, 1.4E-4, 14, 44.77, 11.54, 0.92185, 13, 163.28, 11.79, 0.07801, 3, 15, -63.2, 12.79, 0.03148, 14, 64.32, 11.3, 0.9537, 13, 182.84, 11.67, 0.01482, 2, 15, -43.31, 12.57, 0.13105, 14, 84.21, 11.06, 0.86895, 2, 15, -19.27, 12.3, 0.33545, 14, 108.25, 10.77, 0.66455, 2, 15, 8.76, 11.99, 0.58858, 14, 136.28, 10.42, 0.41142, 2, 15, 29.82, 11.75, 0.81636, 14, 157.34, 10.17, 0.18364, 2, 15, 45.05, 11.58, 0.94514, 14, 172.57, 9.98, 0.05486, 3, 16, -73.48, 10.54, 0.01067, 15, 64.48, 11.36, 0.98334, 14, 192, 9.74, 0.00599, 2, 16, -51.88, 10.54, 0.06672, 15, 86.08, 11.12, 0.93328, 2, 16, -28.02, 10.54, 0.20517, 15, 109.94, 10.86, 0.79483, 2, 16, -6.12, 10.54, 0.43106, 15, 131.84, 10.61, 0.56894, 2, 16, 14.58, 10.54, 0.67732, 15, 152.53, 10.38, 0.32268, 2, 16, 34.91, 10.54, 0.86986, 15, 172.86, 10.15, 0.13014, 2, 16, 55.73, 10.54, 0.96663, 15, 193.68, 9.92, 0.03337, 3, 17, -32.35, 13.24, 0.03704, 16, 80.67, 10.54, 0.96063, 15, 218.62, 9.64, 0.00233, 2, 17, -10.44, 12.98, 0.14815, 16, 102.58, 10.54, 0.85185, 2, 17, 10.25, 12.73, 0.37037, 16, 123.28, 10.54, 0.62963, 2, 17, 33.6, 12.45, 0.62963, 16, 146.63, 10.54, 0.37037, 3, 18, -73.66, 9.72, 0.01481, 17, 55.31, 12.19, 0.83704, 16, 168.34, 10.54, 0.14815, 3, 18, -49.17, 10.25, 0.08034, 17, 79.8, 11.9, 0.88263, 16, 192.83, 10.54, 0.03704, 2, 18, -21.59, 10.85, 0.23361, 17, 107.38, 11.57, 0.76639, 2, 18, -3.69, 11.24, 0.46724, 17, 125.29, 11.35, 0.53276, 3, 19, -85.85, 10.81, 0.03704, 18, 16.27, 11.67, 0.67351, 17, 145.25, 11.12, 0.28945, 3, 19, -55.12, 11.27, 0.1471, 18, 47, 12.34, 0.74238, 17, 175.99, 10.75, 0.11053, 3, 19, -30.63, 11.63, 0.36721, 18, 71.48, 12.87, 0.60716, 17, 200.48, 10.45, 0.02563, 3, 19, -6.03, 12, 0.62331, 18, 96.08, 13.41, 0.37555, 17, 225.08, 10.16, 0.00114, 3, 20, -83.91, 13.62, 0.00655, 19, 19.86, 12.38, 0.83794, 18, 121.97, 13.97, 0.15552, 3, 20, -57.09, 13.62, 0.05647, 19, 46.67, 12.78, 0.90017, 18, 148.78, 14.55, 0.04335, 3, 20, -33.41, 13.62, 0.18681, 19, 70.35, 13.13, 0.81003, 18, 172.45, 15.07, 0.00316, 3, 20, -9.44, 13.62, 0.41497, 19, 94.32, 13.48, 0.58398, 18, 196.42, 15.59, 0.00105, 2, 20, 20.24, 13.62, 0.66748, 19, 124, 13.92, 0.33252, 3, 21, -68.43, 14.05, 0.00769, 20, 48.52, 13.62, 0.86258, 19, 152.28, 14.34, 0.12973, 3, 21, -44.64, 13.9, 0.05327, 20, 72.32, 13.62, 0.91563, 19, 176.07, 14.69, 0.0311, 3, 21, -22.23, 13.76, 0.17378, 20, 94.73, 13.62, 0.82602, 19, 198.48, 15.03, 2.0E-4, 2, 21, -9.45, 13.68, 0.38319, 20, 107.51, 13.62, 0.61681, 2, 21, 9.54, 13.57, 0.62792, 20, 126.5, 13.62, 0.37208, 2, 21, 33.16, 13.42, 0.83391, 20, 150.11, 13.62, 0.16609, 3, 22, -68.06, 15.89, 0.01835, 21, 58.34, 13.26, 0.93179, 20, 175.3, 13.62, 0.04986, 3, 22, -41.18, 15.3, 0.09209, 21, 85.23, 13.1, 0.90107, 20, 202.19, 13.62, 0.00684, 2, 22, -21.14, 14.86, 0.25825, 21, 105.27, 12.97, 0.74175, 2, 22, -1.74, 14.44, 0.49883, 21, 124.68, 12.86, 0.50117, 2, 22, 18.56, 13.99, 0.73973, 21, 144.98, 12.73, 0.26027, 2, 22, 45.59, 13.4, 0.9069, 21, 172.02, 12.56, 0.0931, 3, 23, -68.2, 8.97, 0.01266, 22, 73.36, 12.79, 0.96865, 21, 199.79, 12.39, 0.01869, 2, 23, -48.21, 9.66, 0.07503, 22, 93.35, 12.36, 0.92497, 2, 23, -23.46, 10.51, 0.22413, 22, 118.11, 11.82, 0.77587, 2, 23, -5.63, 11.13, 0.45901, 22, 135.95, 11.43, 0.54099, 3, 24, -88.47, 14.87, 4.9E-4, 23, 22.72, 12.1, 0.70512, 22, 164.31, 10.81, 0.29439, 3, 24, -58.46, 14.71, 0.02937, 23, 52.72, 13.14, 0.86048, 22, 194.32, 10.15, 0.11016, 3, 24, -35.54, 14.59, 0.12366, 23, 75.62, 13.93, 0.85197, 22, 217.23, 9.65, 0.02437, 2, 24, -20.59, 14.51, 0.31892, 23, 90.57, 14.44, 0.68108, 2, 24, 7.78, 14.35, 0.56854, 23, 118.92, 15.42, 0.43146, 3, 25, -110.42, 12.01, 0.00402, 24, 33.07, 14.22, 0.79441, 23, 144.19, 16.29, 0.20157, 3, 25, -78.67, 12.47, 0.0384, 24, 64.82, 14.05, 0.8976, 23, 175.92, 17.39, 0.06399, 3, 25, -42.57, 13, 0.14018, 24, 100.92, 13.85, 0.85067, 23, 212, 18.63, 0.00915, 2, 25, -14.17, 13.42, 0.33433, 24, 129.32, 13.7, 0.66567, 2, 25, 6.23, 13.72, 0.57887, 24, 149.72, 13.59, 0.42113, 3, 26, -127.68, 15.93, 0.02404, 25, 28.43, 14.04, 0.77568, 24, 171.93, 13.47, 0.20028, 3, 26, -89.8, 15.93, 0.10916, 25, 66.3, 14.6, 0.82572, 24, 209.8, 13.27, 0.06511, 3, 26, -33, 15.93, 0.2924, 25, 123.1, 15.43, 0.6969, 24, 266.61, 12.96, 0.0107, 3, 27, -126.58, 18.82, 0.01925, 26, 6.45, 15.93, 0.51941, 25, 162.55, 16, 0.46133, 3, 27, -91.88, 17.84, 0.0948, 26, 41.17, 15.93, 0.67909, 25, 197.26, 16.51, 0.22612, 3, 27, -35.1, 16.24, 0.26366, 26, 97.98, 15.93, 0.66031, 25, 254.06, 17.34, 0.07602, 4, 3, 2844.79, 386.71, 0.03704, 27, 1.18, 15.22, 0.4681, 26, 134.27, 15.93, 0.48187, 25, 290.35, 17.87, 0.01299, 3, 3, 2885.82, 386.76, 0.14815, 27, 42.2, 14.07, 0.59698, 26, 175.3, 15.93, 0.25487, 3, 3, 2931.36, 386.8, 0.37037, 27, 87.72, 12.78, 0.53922, 26, 220.84, 15.93, 0.09041 ],
				"hull": 165,
				"edges": [ 120, 122, 0, 328, 122, 124, 124, 126, 126, 128, 128, 130, 130, 132, 132, 134, 134, 136, 136, 138, 306, 308, 312, 314, 314, 316, 316, 318, 318, 320, 320, 322, 322, 324, 324, 326, 326, 328, 0, 2, 2, 4, 4, 6, 6, 8, 8, 10, 10, 12, 12, 14, 14, 16, 16, 18, 18, 20, 20, 22, 22, 24, 24, 26, 26, 28, 28, 30, 30, 32, 32, 34, 34, 36, 36, 38, 38, 40, 40, 42, 42, 44, 44, 46, 46, 48, 48, 50, 50, 52, 52, 54, 54, 56, 56, 58, 58, 60, 60, 62, 62, 64, 64, 66, 66, 68, 68, 70, 70, 72, 72, 74, 74, 76, 76, 78, 78, 80, 80, 82, 82, 84, 84, 86, 86, 88, 88, 90, 90, 92, 92, 94, 94, 96, 96, 98, 98, 100, 100, 102, 102, 104, 104, 106, 106, 108, 108, 110, 110, 112, 112, 114, 114, 116, 116, 118, 118, 120, 138, 140, 140, 142, 142, 144, 144, 146, 146, 148, 148, 150, 150, 152, 152, 154, 154, 156, 156, 158, 158, 160, 160, 162, 162, 164, 164, 166, 166, 168, 168, 170, 170, 172, 172, 174, 174, 176, 176, 178, 178, 180, 180, 182, 182, 184, 184, 186, 186, 188, 188, 190, 190, 192, 192, 194, 194, 196, 196, 198, 198, 200, 200, 202, 202, 204, 204, 206, 206, 208, 208, 210, 210, 212, 212, 214, 214, 216, 216, 218, 218, 220, 220, 222, 222, 224, 224, 226, 226, 228, 228, 230, 230, 232, 232, 234, 234, 236, 236, 238, 238, 240, 240, 242, 242, 244, 244, 246, 246, 248, 248, 250, 250, 252, 252, 254, 254, 256, 256, 258, 258, 260, 260, 262, 262, 264, 264, 266, 266, 268, 268, 270, 270, 272, 272, 274, 274, 276, 276, 278, 278, 280, 280, 282, 282, 284, 284, 286, 286, 288, 288, 290, 290, 292, 292, 294, 294, 296, 296, 298, 298, 300, 300, 302, 302, 304, 304, 306, 308, 310, 310, 312 ],
				"width": 1402,
				"height": 492
			}
		},
		"water": {
			"water": {
				"type": "path",
				"lengths": [ 88.28, 148.32, 208.6, 272.15, 328.27, 385.01, 445.29, 514.92, 570.88, 630.07, 701.76, 757.69, 822.69, 876.45, 930.75, 993.04, 1053.86, 1117.39, 1184.03, 1244.85, 1316.03, 1381.75, 1425.81, 2877.47 ],
				"vertexCount": 72,
				"vertices": [ -1578.28, -294, -1525.94, -287.18, -1475.89, -280.66, -1393.97, -287.61, -1349.49, -287.12, -1305.02, -286.63, -1265.62, -284.57, -1229.46, -283.92, -1193.3, -283.27, -1146.06, -281.75, -1108.91, -281.75, -1071.77, -281.75, -1017.83, -284.08, -981.85, -283.92, -945.87, -283.76, -903.49, -281.83, -869.63, -281.18, -835.78, -280.53, -791.2, -282.5, -756.17, -282.66, -721.15, -282.82, -674.6, -281.26, -635.63, -281.75, -596.66, -282.24, -534.03, -283.16, -496.36, -282.83, -458.68, -282.51, -419.04, -280.07, -384.5, -279.58, -349.96, -279.09, -305.39, -279.74, -266.13, -279.58, -226.86, -279.41, -161.04, -278.49, -122.75, -278.49, -84.46, -278.49, -47.17, -279.25, -10.89, -279.58, 25.39, -279.9, 83.48, -280.66, 119.11, -280.66, 154.74, -280.66, 194.21, -279.58, 226.62, -279.58, 259.04, -279.58, 300.25, -280.66, 335.22, -280.66, 370.2, -280.66, 422.86, -279.74, 459.79, -279.58, 496.72, -279.41, 544.12, -279.41, 581.42, -279.58, 618.73, -279.74, 669.44, -280.99, 708.49, -280.66, 747.54, -280.34, 803.49, -277.89, 841.72, -277.4, 879.95, -276.92, 923.76, -276.59, 963.35, -277.4, 1002.94, -278.22, 1064.55, -282.35, 1105.62, -282.84, 1146.68, -283.32, 1204.1, -280.34, 1237.02, -280.66, 1269.95, -280.99, 1294.83, -285.76, 1325.02, -285.01, 1351.44, -284.35 ]
			}
		}
	}
},
"animations": {
	"animation": {
		"deform": {
			"default": {
				"water": {
					"water": [
						{
							"time": 0,
							"vertices": [ 1.53552, 3.94153, 0, 4.10921, 0.78003, 4.5787, -23.35193, 18.57678, -23.35193, 18.3266, -23.35193, 18.07642, 0, 8.10477, 0, 2.44136, -1.36955, -3.03225, 0, -9.25406, 6.0E-5, -9.25406, 0, -9.25406, -0.78003, -2.80507, 0, 2.44136, -1.53129, 7.34765, 2.50214, 13.17496, 2.50214, 12.84138, 2.50214, 12.5078, -1.56018, 6.66209, 0, 1.79637, -1.31093, -2.67476, 3.33612, -10.31834, 3.33612, -10.06816, 3.33609, -9.81798, 0, -3.27762, 0, 1.88542, -1.57262, 6.81934, 5.00406, 12.27251, 5.00406, 12.02231, 5.00404, 11.77209, -0.77997, 5.25011, -2.0E-5, 0.21759, -1.16446, -4.57847, 0.83398, -11.73596, 0.83399, -11.73596, 0.83398, -11.73596, 0, -5.27904, 0, 0.21761, -1.45307, 5.50713, -0.834, 11.35709, -0.834, 11.35709, -0.83398, 11.35709, -1.56, 4.78606, 0, 0.21762, -1.16415, -3.98456, 7.50604, -8.58884, 7.50604, -8.58884, 7.50604, -8.58884, 0, -5.02885, 0, 0.21761, -1.55815, 5.23581, -1.66797, 11.1248, -1.66797, 11.20821, -1.66797, 11.2916, 4.67993, 5.88948, 0, 0.77354, -1.4995, -4.78566, 1.66809, -13.26294, 1.66809, -13.51314, 1.66809, -13.76334, 0, -9.68678, 0, -0.89429, -2.98834, 7.29605, 1.66809, 19.13873, 1.66809, 19.38901, 1.66809, 19.63927, 2.33997, 5.55582, 0, 0.77354, -1.77172, -4.10361, 1.66797, -6.79477, 1.66797, -7.17917, 1.66797, -7.51561 ]
						},
						{
							"time": 0.8333,
							"vertices": [ 5.4423, 36.74341, 2.50208, 22.4073, -0.61792, 8.74612, -20.43298, 10.69128, -20.43298, 10.40019, -20.43298, 10.10912, -0.83398, 21.86665, -0.83398, 21.47856, -0.83398, 21.09045, 2.99615, 13.43097, 0.83405, 8.38094, 0.83405, 3.0188, 1.66815, -2.03229, 1.66815, -2.12936, 1.66815, -2.22639, 6.66983, 0.0624, 2.91913, 5.67944, 2.13916, 11.91512, 3.33594, 19.28203, 3.33594, 19.37907, 3.33594, 19.4761, 7.76163, 12.1587, 3.75311, 5.68289, 2.19318, -1.28064, -4.17004, -4.60562, -4.17004, -4.7997, -4.17004, -4.99379, 7.08997, 0.92159, 5.42105, 4.72644, 6.20103, 8.8512, 0.83398, 14.2666, 0.83398, 14.16959, 0.83398, 14.07257, 0.83398, 8.49553, 0.83398, 4.07968, -0.6343, -0.16684, -1.66798, -7.2715, -1.66798, -7.07747, -1.66798, -6.88342, 1.41875, 1.68527, 0, 5.71057, -0.77997, 9.811, 0, 13.49513, 3.0E-5, 13.49513, 0, 13.49513, 6.78014, 8.50565, 8.3401, 5.03604, 7.41383, 1.80254, 0.83398, -4.61966, 0.83398, -4.71669, 0.83398, -4.81372, -0.98257, -0.20425, -2.50195, 4.22059, -3.28192, 8.73347, -7.50604, 15.34781, -7.50604, 15.15372, -7.50604, 14.95964, 2.1944, 5.99016, 0.83411, 1.40926, 6.29395, -3.92856, 3.33606, -7.8446, 3.33606, -7.35939, 3.33606, -6.87418, 5.06127, 5.21918, 3.75305, 9.87093, 2.97302, 14.57796, 0.83398, 16.98309, 0.83398, 17.17726, 0.83398, 17.37141, -0.41711, 10.09419, -0.41711, 9.64694, -0.41711, 9.25549 ]
						},
						{
							"time": 1.6667,
							"offset": 1,
							"vertices": [ 8.00562, 0, 4.90302, 0, 1.93633, -17.51404, -5.80888, -17.51404, -6.03127, -17.51404, -6.25365, 3.26176, -4.11502, 0, 3.42049, -3.19983, 10.97141, 1.66809, 22.42999, 1.66809, 22.42999, 1.66809, 22.42999, 0, 10.47008, 0, 3.42049, -2.03263, -3.24004, 3.33612, -8.89403, 3.33612, -9.19054, 3.33612, -9.48705, 1.84326, -3.427, 0, 2.84715, 0, 9.46077, 4.1701, 15.84467, 4.1701, 16.06705, 4.1701, 16.28943, 0, 7.87022, 0, 2.92633, -0.91694, -1.90519, 5.83804, -9.69621, 5.83804, -9.91861, 5.83804, -10.14102, 1.2971, -3.84834, 0, 1.44379, 0.79999, 7.03725, 0.83399, 15.49356, 0.83399, 15.49356, 0.83399, 15.49356, 3.19992, 6.09119, 0, 1.4438, -1.30503, -3.48846, 0.83398, -7.15193, 0.83398, -7.15193, 0.83398, -7.15193, 1.4164, -3.72123, 0, 1.44382, 1.59998, 7.11139, 9.17416, 13.30038, 9.17416, 13.30038, 9.17416, 13.30038, 0.79999, 7.1855, 0, 1.4438, -1.39837, -4.2055, -3.33594, -10.44722, -3.33594, -10.37309, -3.33594, -10.29897, 2.3999, -4.01729, 0, 1.93797, -1.79736, 7.9965, 1.2E-4, 11.13127, 1.2E-4, 10.90887, 1.2E-4, 10.68648, 2.40002, 5.31636, 0, 0.45546, -1.4585, -4.54912, 5.83801, -6.38606, 5.83801, -6.16362, 5.83801, -5.94115, 0, -4.74986, 0, 1.93799, -1.89124, 8.26043, -2.5022, 21.9817, -2.5022, 21.64, -2.5022, 21.34094 ]
						},
						{
							"time": 2.5,
							"vertices": [ 1.66797, 31.62943, 1.66797, 22.19772, 1.66797, 13.17914, -18.55323, 15.52565, -20.43298, 10.12985, -18.03296, 4.24096, -1.66797, -6.66167, -1.66797, -7.56302, -1.66797, -8.46437, 4.83405, -2.40634, 0.83411, 1.57994, -0.86956, 5.84239, 5.00397, 17.27699, 5.00397, 17.05159, 5.00397, 16.82617, 4.74113, 7.88489, 2.91919, 3.02635, 1.31915, -1.86133, 0, -2.17888, 0, -1.95351, 0, -1.72815, 4.55316, -0.52504, 3.75311, 4.1373, 2.26116, 8.72395, 0, 16.00009, 0, 15.54935, 0, 15.09859, 9.07128, 7.22823, 5.42105, 0.81306, 5.42105, -6.30243, 2.50211, -9.83041, 2.50211, -10.05574, 2.50211, -10.28105, 3.252, -5.8217, 0.83398, -0.68913, -3.16595, 4.21708, 2.50195, 10.5919, 2.50195, 11.04256, 2.50195, 11.49323, 1.63978, 6.09105, 0, 1.9957, 0, -2.29723, 3.33606, -7.49828, 3.33606, -7.49828, 3.33606, -7.49828, 9.79077, -1.18593, 8.3401, 2.63506, 8.34004, 6.62136, 0.83398, 9.03021, 0.83405, 8.80487, 0.83398, 8.57951, -0.92737, 5.24058, -2.50195, 1.29264, -5.7019, -2.46833, -0.83398, -5.86497, -0.83392, -6.31572, -0.83398, -6.76648, 2.43408, -4.50352, 0.83411, -0.27337, -1.1548, 3.90665, 0, 6.59148, 0, 7.71838, 0, 8.84528, 7.75293, 8.35286, 3.75305, 2.28308, -0.02545, -3.82588, -0.83398, -10.60266, -0.83398, -10.15175, -0.83398, -9.70084, 1.18286, 1.93874, -0.41711, 6.72612, -3.25034, 10.6385 ]
						},
						{
							"time": 3.3333,
							"vertices": [ 1.53552, 3.94153, 0, 4.10921, 0.78003, 4.5787, -23.35193, 18.57678, -23.35193, 18.3266, -23.35193, 18.07642, 0, 8.10477, 0, 2.44136, -1.36955, -3.03225, 0, -9.25406, 6.0E-5, -9.25406, 0, -9.25406, -0.78003, -2.80507, 0, 2.44136, -1.53129, 7.34765, 2.50214, 13.17496, 2.50214, 12.84138, 2.50214, 12.5078, -1.56018, 6.66209, 0, 1.79637, -1.31093, -2.67476, 3.33612, -10.31834, 3.33612, -10.06816, 3.33609, -9.81798, 0, -3.27762, 0, 1.88542, -1.57262, 6.81934, 5.00406, 12.27251, 5.00406, 12.02231, 5.00404, 11.77209, -0.77997, 5.25011, -2.0E-5, 0.21759, -1.16446, -4.57847, 0.83398, -11.73596, 0.83399, -11.73596, 0.83398, -11.73596, 0, -5.27904, 0, 0.21761, -1.45307, 5.50713, -0.834, 11.35709, -0.834, 11.35709, -0.83398, 11.35709, -1.56, 4.78606, 0, 0.21762, -1.16415, -3.98456, 7.50604, -8.58884, 7.50604, -8.58884, 7.50604, -8.58884, 0, -5.02885, 0, 0.21761, -1.55815, 5.23581, -1.66797, 11.1248, -1.66797, 11.20821, -1.66797, 11.2916, 4.67993, 5.88948, 0, 0.77354, -1.4995, -4.78566, 1.66809, -13.26294, 1.66809, -13.51314, 1.66809, -13.76334, 0, -9.68678, 0, -0.89429, -2.98834, 7.29605, 1.66809, 19.13873, 1.66809, 19.38901, 1.66809, 19.63927, 2.33997, 5.55582, 0, 0.77354, -1.77172, -4.10361, 1.66797, -6.79477, 1.66797, -7.17917, 1.66797, -7.51561 ]
						},
						{
							"time": 4.1667,
							"vertices": [ 5.4423, 36.74341, 2.50208, 22.4073, -0.61792, 8.74612, -20.43298, 10.69128, -20.43298, 10.40019, -20.43298, 10.10912, -0.83398, 21.86665, -0.83398, 21.47856, -0.83398, 21.09045, 2.99615, 13.43097, 0.83405, 8.38094, 0.83405, 3.0188, 1.66815, -2.03229, 1.66815, -2.12936, 1.66815, -2.22639, 6.66983, 0.0624, 2.91913, 5.67944, 2.13916, 11.91512, 3.33594, 19.28203, 3.33594, 19.37907, 3.33594, 19.4761, 7.76163, 12.1587, 3.75311, 5.68289, 2.19318, -1.28064, -4.17004, -4.60562, -4.17004, -4.7997, -4.17004, -4.99379, 7.08997, 0.92159, 5.42105, 4.72644, 6.20103, 8.8512, 0.83398, 14.2666, 0.83398, 14.16959, 0.83398, 14.07257, 0.83398, 8.49553, 0.83398, 4.07968, -0.6343, -0.16684, -1.66798, -7.2715, -1.66798, -7.07747, -1.66798, -6.88342, 1.41875, 1.68527, 0, 5.71057, -0.77997, 9.811, 0, 13.49513, 3.0E-5, 13.49513, 0, 13.49513, 6.78014, 8.50565, 8.3401, 5.03604, 7.41383, 1.80254, 0.83398, -4.61966, 0.83398, -4.71669, 0.83398, -4.81372, -0.98257, -0.20425, -2.50195, 4.22059, -3.28192, 8.73347, -7.50604, 15.34781, -7.50604, 15.15372, -7.50604, 14.95964, 2.1944, 5.99016, 0.83411, 1.40926, 6.29395, -3.92856, 3.33606, -7.8446, 3.33606, -7.35939, 3.33606, -6.87418, 5.06127, 5.21918, 3.75305, 9.87093, 2.97302, 14.57796, 0.83398, 16.98309, 0.83398, 17.17726, 0.83398, 17.37141, -0.41711, 10.09419, -0.41711, 9.64694, -0.41711, 9.25549 ]
						},
						{
							"time": 5,
							"offset": 1,
							"vertices": [ 8.00562, 0, 4.90302, 0, 1.93633, -17.51404, -5.80888, -17.51404, -6.03127, -17.51404, -6.25365, 3.26176, -4.11502, 0, 3.42049, -3.19983, 10.97141, 1.66809, 22.42999, 1.66809, 22.42999, 1.66809, 22.42999, 0, 10.47008, 0, 3.42049, -2.03263, -3.24004, 3.33612, -8.89403, 3.33612, -9.19054, 3.33612, -9.48705, 1.84326, -3.427, 0, 2.84715, 0, 9.46077, 4.1701, 15.84467, 4.1701, 16.06705, 4.1701, 16.28943, 0, 7.87022, 0, 2.92633, -0.91694, -1.90519, 5.83804, -9.69621, 5.83804, -9.91861, 5.83804, -10.14102, 1.2971, -3.84834, 0, 1.44379, 0.79999, 7.03725, 0.83399, 15.49356, 0.83399, 15.49356, 0.83399, 15.49356, 3.19992, 6.09119, 0, 1.4438, -1.30503, -3.48846, 0.83398, -7.15193, 0.83398, -7.15193, 0.83398, -7.15193, 1.4164, -3.72123, 0, 1.44382, 1.59998, 7.11139, 9.17416, 13.30038, 9.17416, 13.30038, 9.17416, 13.30038, 0.79999, 7.1855, 0, 1.4438, -1.39837, -4.2055, -3.33594, -10.44722, -3.33594, -10.37309, -3.33594, -10.29897, 2.3999, -4.01729, 0, 1.93797, -1.79736, 7.9965, 1.2E-4, 11.13127, 1.2E-4, 10.90887, 1.2E-4, 10.68648, 2.40002, 5.31636, 0, 0.45546, -1.4585, -4.54912, 5.83801, -6.38606, 5.83801, -6.16362, 5.83801, -5.94115, 0, -4.74986, 0, 1.93799, -1.89124, 8.26043, -2.5022, 21.9817, -2.5022, 21.64, -2.5022, 21.34094 ]
						},
						{
							"time": 5.8333,
							"vertices": [ 1.66797, 31.62943, 1.66797, 22.19772, 1.66797, 13.17914, -18.55323, 15.52565, -20.43298, 10.12985, -18.03296, 4.24096, -1.66797, -6.66167, -1.66797, -7.56302, -1.66797, -8.46437, 4.83405, -2.40634, 0.83411, 1.57994, -0.86956, 5.84239, 5.00397, 17.27699, 5.00397, 17.05159, 5.00397, 16.82617, 4.74113, 7.88489, 2.91919, 3.02635, 1.31915, -1.86133, 0, -2.17888, 0, -1.95351, 0, -1.72815, 4.55316, -0.52504, 3.75311, 4.1373, 2.26116, 8.72395, 0, 16.00009, 0, 15.54935, 0, 15.09859, 9.07128, 7.22823, 5.42105, 0.81306, 5.42105, -6.30243, 2.50211, -9.83041, 2.50211, -10.05574, 2.50211, -10.28105, 3.252, -5.8217, 0.83398, -0.68913, -3.16595, 4.21708, 2.50195, 10.5919, 2.50195, 11.04256, 2.50195, 11.49323, 1.63978, 6.09105, 0, 1.9957, 0, -2.29723, 3.33606, -7.49828, 3.33606, -7.49828, 3.33606, -7.49828, 9.79077, -1.18593, 8.3401, 2.63506, 8.34004, 6.62136, 0.83398, 9.03021, 0.83405, 8.80487, 0.83398, 8.57951, -0.92737, 5.24058, -2.50195, 1.29264, -5.7019, -2.46833, -0.83398, -5.86497, -0.83392, -6.31572, -0.83398, -6.76648, 2.43408, -4.50352, 0.83411, -0.27337, -1.1548, 3.90665, 0, 6.59148, 0, 7.71838, 0, 8.84528, 7.75293, 8.35286, 3.75305, 2.28308, -0.02545, -3.82588, -0.83398, -10.60266, -0.83398, -10.15175, -0.83398, -9.70084, 1.18286, 1.93874, -0.41711, 6.72612, -3.25034, 10.6385 ]
						},
						{
							"time": 6.6667,
							"vertices": [ 1.53552, 3.94153, 0, 4.10921, 0.78003, 4.5787, -23.35193, 18.57678, -23.35193, 18.3266, -23.35193, 18.07642, 0, 8.10477, 0, 2.44136, -1.36955, -3.03225, 0, -9.25406, 6.0E-5, -9.25406, 0, -9.25406, -0.78003, -2.80507, 0, 2.44136, -1.53129, 7.34765, 2.50214, 13.17496, 2.50214, 12.84138, 2.50214, 12.5078, -1.56018, 6.66209, 0, 1.79637, -1.31093, -2.67476, 3.33612, -10.31834, 3.33612, -10.06816, 3.33609, -9.81798, 0, -3.27762, 0, 1.88542, -1.57262, 6.81934, 5.00406, 12.27251, 5.00406, 12.02231, 5.00404, 11.77209, -0.77997, 5.25011, -2.0E-5, 0.21759, -1.16446, -4.57847, 0.83398, -11.73596, 0.83399, -11.73596, 0.83398, -11.73596, 0, -5.27904, 0, 0.21761, -1.45307, 5.50713, -0.834, 11.35709, -0.834, 11.35709, -0.83398, 11.35709, -1.56, 4.78606, 0, 0.21762, -1.16415, -3.98456, 7.50604, -8.58884, 7.50604, -8.58884, 7.50604, -8.58884, 0, -5.02885, 0, 0.21761, -1.55815, 5.23581, -1.66797, 11.1248, -1.66797, 11.20821, -1.66797, 11.2916, 4.67993, 5.88948, 0, 0.77354, -1.4995, -4.78566, 1.66809, -13.26294, 1.66809, -13.51314, 1.66809, -13.76334, 0, -9.68678, 0, -0.89429, -2.98834, 7.29605, 1.66809, 19.13873, 1.66809, 19.38901, 1.66809, 19.63927, 2.33997, 5.55582, 0, 0.77354, -1.77172, -4.10361, 1.66797, -6.79477, 1.66797, -7.17917, 1.66797, -7.51561 ]
						},
						{
							"time": 7.5,
							"vertices": [ 5.4423, 36.74341, 2.50208, 22.4073, -0.61792, 8.74612, -20.43298, 10.69128, -20.43298, 10.40019, -20.43298, 10.10912, -0.83398, 21.86665, -0.83398, 21.47856, -0.83398, 21.09045, 2.99615, 13.43097, 0.83405, 8.38094, 0.83405, 3.0188, 1.66815, -2.03229, 1.66815, -2.12936, 1.66815, -2.22639, 6.66983, 0.0624, 2.91913, 5.67944, 2.13916, 11.91512, 3.33594, 19.28203, 3.33594, 19.37907, 3.33594, 19.4761, 7.76163, 12.1587, 3.75311, 5.68289, 2.19318, -1.28064, -4.17004, -4.60562, -4.17004, -4.7997, -4.17004, -4.99379, 7.08997, 0.92159, 5.42105, 4.72644, 6.20103, 8.8512, 0.83398, 14.2666, 0.83398, 14.16959, 0.83398, 14.07257, 0.83398, 8.49553, 0.83398, 4.07968, -0.6343, -0.16684, -1.66798, -7.2715, -1.66798, -7.07747, -1.66798, -6.88342, 1.41875, 1.68527, 0, 5.71057, -0.77997, 9.811, 0, 13.49513, 3.0E-5, 13.49513, 0, 13.49513, 6.78014, 8.50565, 8.3401, 5.03604, 7.41383, 1.80254, 0.83398, -4.61966, 0.83398, -4.71669, 0.83398, -4.81372, -0.98257, -0.20425, -2.50195, 4.22059, -3.28192, 8.73347, -7.50604, 15.34781, -7.50604, 15.15372, -7.50604, 14.95964, 2.1944, 5.99016, 0.83411, 1.40926, 6.29395, -3.92856, 3.33606, -7.8446, 3.33606, -7.35939, 3.33606, -6.87418, 5.06127, 5.21918, 3.75305, 9.87093, 2.97302, 14.57796, 0.83398, 16.98309, 0.83398, 17.17726, 0.83398, 17.37141, -0.41711, 10.09419, -0.41711, 9.64694, -0.41711, 9.25549 ]
						},
						{
							"time": 8.3333,
							"offset": 1,
							"vertices": [ 8.00562, 0, 4.90302, 0, 1.93633, -17.51404, -5.80888, -17.51404, -6.03127, -17.51404, -6.25365, 3.26176, -4.11502, 0, 3.42049, -3.19983, 10.97141, 1.66809, 22.42999, 1.66809, 22.42999, 1.66809, 22.42999, 0, 10.47008, 0, 3.42049, -2.03263, -3.24004, 3.33612, -8.89403, 3.33612, -9.19054, 3.33612, -9.48705, 1.84326, -3.427, 0, 2.84715, 0, 9.46077, 4.1701, 15.84467, 4.1701, 16.06705, 4.1701, 16.28943, 0, 7.87022, 0, 2.92633, -0.91694, -1.90519, 5.83804, -9.69621, 5.83804, -9.91861, 5.83804, -10.14102, 1.2971, -3.84834, 0, 1.44379, 0.79999, 7.03725, 0.83399, 15.49356, 0.83399, 15.49356, 0.83399, 15.49356, 3.19992, 6.09119, 0, 1.4438, -1.30503, -3.48846, 0.83398, -7.15193, 0.83398, -7.15193, 0.83398, -7.15193, 1.4164, -3.72123, 0, 1.44382, 1.59998, 7.11139, 9.17416, 13.30038, 9.17416, 13.30038, 9.17416, 13.30038, 0.79999, 7.1855, 0, 1.4438, -1.39837, -4.2055, -3.33594, -10.44722, -3.33594, -10.37309, -3.33594, -10.29897, 2.3999, -4.01729, 0, 1.93797, -1.79736, 7.9965, 1.2E-4, 11.13127, 1.2E-4, 10.90887, 1.2E-4, 10.68648, 2.40002, 5.31636, 0, 0.45546, -1.4585, -4.54912, 5.83801, -6.38606, 5.83801, -6.16362, 5.83801, -5.94115, 0, -4.74986, 0, 1.93799, -1.89124, 8.26043, -2.5022, 21.9817, -2.5022, 21.64, -2.5022, 21.34094 ]
						},
						{
							"time": 9.1667,
							"vertices": [ 1.66797, 31.62943, 1.66797, 22.19772, 1.66797, 13.17914, -18.55323, 15.52565, -20.43298, 10.12985, -18.03296, 4.24096, -1.66797, -6.66167, -1.66797, -7.56302, -1.66797, -8.46437, 4.83405, -2.40634, 0.83411, 1.57994, -0.86956, 5.84239, 5.00397, 17.27699, 5.00397, 17.05159, 5.00397, 16.82617, 4.74113, 7.88489, 2.91919, 3.02635, 1.31915, -1.86133, 0, -2.17888, 0, -1.95351, 0, -1.72815, 4.55316, -0.52504, 3.75311, 4.1373, 2.26116, 8.72395, 0, 16.00009, 0, 15.54935, 0, 15.09859, 9.07128, 7.22823, 5.42105, 0.81306, 5.42105, -6.30243, 2.50211, -9.83041, 2.50211, -10.05574, 2.50211, -10.28105, 3.252, -5.8217, 0.83398, -0.68913, -3.16595, 4.21708, 2.50195, 10.5919, 2.50195, 11.04256, 2.50195, 11.49323, 1.63978, 6.09105, 0, 1.9957, 0, -2.29723, 3.33606, -7.49828, 3.33606, -7.49828, 3.33606, -7.49828, 9.79077, -1.18593, 8.3401, 2.63506, 8.34004, 6.62136, 0.83398, 9.03021, 0.83405, 8.80487, 0.83398, 8.57951, -0.92737, 5.24058, -2.50195, 1.29264, -5.7019, -2.46833, -0.83398, -5.86497, -0.83392, -6.31572, -0.83398, -6.76648, 2.43408, -4.50352, 0.83411, -0.27337, -1.1548, 3.90665, 0, 6.59148, 0, 7.71838, 0, 8.84528, 7.75293, 8.35286, 3.75305, 2.28308, -0.02545, -3.82588, -0.83398, -10.60266, -0.83398, -10.15175, -0.83398, -9.70084, 1.18286, 1.93874, -0.41711, 6.72612, -3.25034, 10.6385 ]
						},
						{
							"time": 10,
							"vertices": [ 1.53552, 3.94153, 0, 4.10921, 0.78003, 4.5787, -23.35193, 18.57678, -23.35193, 18.3266, -23.35193, 18.07642, 0, 8.10477, 0, 2.44136, -1.36955, -3.03225, 0, -9.25406, 6.0E-5, -9.25406, 0, -9.25406, -0.78003, -2.80507, 0, 2.44136, -1.53129, 7.34765, 2.50214, 13.17496, 2.50214, 12.84138, 2.50214, 12.5078, -1.56018, 6.66209, 0, 1.79637, -1.31093, -2.67476, 3.33612, -10.31834, 3.33612, -10.06816, 3.33609, -9.81798, 0, -3.27762, 0, 1.88542, -1.57262, 6.81934, 5.00406, 12.27251, 5.00406, 12.02231, 5.00404, 11.77209, -0.77997, 5.25011, -2.0E-5, 0.21759, -1.16446, -4.57847, 0.83398, -11.73596, 0.83399, -11.73596, 0.83398, -11.73596, 0, -5.27904, 0, 0.21761, -1.45307, 5.50713, -0.834, 11.35709, -0.834, 11.35709, -0.83398, 11.35709, -1.56, 4.78606, 0, 0.21762, -1.16415, -3.98456, 7.50604, -8.58884, 7.50604, -8.58884, 7.50604, -8.58884, 0, -5.02885, 0, 0.21761, -1.55815, 5.23581, -1.66797, 11.1248, -1.66797, 11.20821, -1.66797, 11.2916, 4.67993, 5.88948, 0, 0.77354, -1.4995, -4.78566, 1.66809, -13.26294, 1.66809, -13.51314, 1.66809, -13.76334, 0, -9.68678, 0, -0.89429, -2.98834, 7.29605, 1.66809, 19.13873, 1.66809, 19.38901, 1.66809, 19.63927, 2.33997, 5.55582, 0, 0.77354, -1.77172, -4.10361, 1.66797, -6.79477, 1.66797, -7.17917, 1.66797, -7.51561 ]
						},
						{
							"time": 10.8333,
							"vertices": [ 5.4423, 36.74341, 2.50208, 22.4073, -0.61792, 8.74612, -20.43298, 10.69128, -20.43298, 10.40019, -20.43298, 10.10912, -0.83398, 21.86665, -0.83398, 21.47856, -0.83398, 21.09045, 2.99615, 13.43097, 0.83405, 8.38094, 0.83405, 3.0188, 1.66815, -2.03229, 1.66815, -2.12936, 1.66815, -2.22639, 6.66983, 0.0624, 2.91913, 5.67944, 2.13916, 11.91512, 3.33594, 19.28203, 3.33594, 19.37907, 3.33594, 19.4761, 7.76163, 12.1587, 3.75311, 5.68289, 2.19318, -1.28064, -4.17004, -4.60562, -4.17004, -4.7997, -4.17004, -4.99379, 7.08997, 0.92159, 5.42105, 4.72644, 6.20103, 8.8512, 0.83398, 14.2666, 0.83398, 14.16959, 0.83398, 14.07257, 0.83398, 8.49553, 0.83398, 4.07968, -0.6343, -0.16684, -1.66798, -7.2715, -1.66798, -7.07747, -1.66798, -6.88342, 1.41875, 1.68527, 0, 5.71057, -0.77997, 9.811, 0, 13.49513, 3.0E-5, 13.49513, 0, 13.49513, 6.78014, 8.50565, 8.3401, 5.03604, 7.41383, 1.80254, 0.83398, -4.61966, 0.83398, -4.71669, 0.83398, -4.81372, -0.98257, -0.20425, -2.50195, 4.22059, -3.28192, 8.73347, -7.50604, 15.34781, -7.50604, 15.15372, -7.50604, 14.95964, 2.1944, 5.99016, 0.83411, 1.40926, 6.29395, -3.92856, 3.33606, -7.8446, 3.33606, -7.35939, 3.33606, -6.87418, 5.06127, 5.21918, 3.75305, 9.87093, 2.97302, 14.57796, 0.83398, 16.98309, 0.83398, 17.17726, 0.83398, 17.37141, -0.41711, 10.09419, -0.41711, 9.64694, -0.41711, 9.25549 ]
						},
						{
							"time": 11.6667,
							"offset": 1,
							"vertices": [ 8.00562, 0, 4.90302, 0, 1.93633, -17.51404, -5.80888, -17.51404, -6.03127, -17.51404, -6.25365, 3.26176, -4.11502, 0, 3.42049, -3.19983, 10.97141, 1.66809, 22.42999, 1.66809, 22.42999, 1.66809, 22.42999, 0, 10.47008, 0, 3.42049, -2.03263, -3.24004, 3.33612, -8.89403, 3.33612, -9.19054, 3.33612, -9.48705, 1.84326, -3.427, 0, 2.84715, 0, 9.46077, 4.1701, 15.84467, 4.1701, 16.06705, 4.1701, 16.28943, 0, 7.87022, 0, 2.92633, -0.91694, -1.90519, 5.83804, -9.69621, 5.83804, -9.91861, 5.83804, -10.14102, 1.2971, -3.84834, 0, 1.44379, 0.79999, 7.03725, 0.83399, 15.49356, 0.83399, 15.49356, 0.83399, 15.49356, 3.19992, 6.09119, 0, 1.4438, -1.30503, -3.48846, 0.83398, -7.15193, 0.83398, -7.15193, 0.83398, -7.15193, 1.4164, -3.72123, 0, 1.44382, 1.59998, 7.11139, 9.17416, 13.30038, 9.17416, 13.30038, 9.17416, 13.30038, 0.79999, 7.1855, 0, 1.4438, -1.39837, -4.2055, -3.33594, -10.44722, -3.33594, -10.37309, -3.33594, -10.29897, 2.3999, -4.01729, 0, 1.93797, -1.79736, 7.9965, 1.2E-4, 11.13127, 1.2E-4, 10.90887, 1.2E-4, 10.68648, 2.40002, 5.31636, 0, 0.45546, -1.4585, -4.54912, 5.83801, -6.38606, 5.83801, -6.16362, 5.83801, -5.94115, 0, -4.74986, 0, 1.93799, -1.89124, 8.26043, -2.5022, 21.9817, -2.5022, 21.64, -2.5022, 21.34094 ]
						},
						{
							"time": 12.5,
							"vertices": [ 1.66797, 31.62943, 1.66797, 22.19772, 1.66797, 13.17914, -18.55323, 15.52565, -20.43298, 10.12985, -18.03296, 4.24096, -1.66797, -6.66167, -1.66797, -7.56302, -1.66797, -8.46437, 4.83405, -2.40634, 0.83411, 1.57994, -0.86956, 5.84239, 5.00397, 17.27699, 5.00397, 17.05159, 5.00397, 16.82617, 4.74113, 7.88489, 2.91919, 3.02635, 1.31915, -1.86133, 0, -2.17888, 0, -1.95351, 0, -1.72815, 4.55316, -0.52504, 3.75311, 4.1373, 2.26116, 8.72395, 0, 16.00009, 0, 15.54935, 0, 15.09859, 9.07128, 7.22823, 5.42105, 0.81306, 5.42105, -6.30243, 2.50211, -9.83041, 2.50211, -10.05574, 2.50211, -10.28105, 3.252, -5.8217, 0.83398, -0.68913, -3.16595, 4.21708, 2.50195, 10.5919, 2.50195, 11.04256, 2.50195, 11.49323, 1.63978, 6.09105, 0, 1.9957, 0, -2.29723, 3.33606, -7.49828, 3.33606, -7.49828, 3.33606, -7.49828, 9.79077, -1.18593, 8.3401, 2.63506, 8.34004, 6.62136, 0.83398, 9.03021, 0.83405, 8.80487, 0.83398, 8.57951, -0.92737, 5.24058, -2.50195, 1.29264, -5.7019, -2.46833, -0.83398, -5.86497, -0.83392, -6.31572, -0.83398, -6.76648, 2.43408, -4.50352, 0.83411, -0.27337, -1.1548, 3.90665, 0, 6.59148, 0, 7.71838, 0, 8.84528, 7.75293, 8.35286, 3.75305, 2.28308, -0.02545, -3.82588, -0.83398, -10.60266, -0.83398, -10.15175, -0.83398, -9.70084, 1.18286, 1.93874, -0.41711, 6.72612, -3.25034, 10.6385 ]
						},
						{
							"time": 13.3333,
							"vertices": [ 1.53552, 3.94153, 0, 4.10921, 0.78003, 4.5787, -23.35193, 18.57678, -23.35193, 18.3266, -23.35193, 18.07642, 0, 8.10477, 0, 2.44136, -1.36955, -3.03225, 0, -9.25406, 6.0E-5, -9.25406, 0, -9.25406, -0.78003, -2.80507, 0, 2.44136, -1.53129, 7.34765, 2.50214, 13.17496, 2.50214, 12.84138, 2.50214, 12.5078, -1.56018, 6.66209, 0, 1.79637, -1.31093, -2.67476, 3.33612, -10.31834, 3.33612, -10.06816, 3.33609, -9.81798, 0, -3.27762, 0, 1.88542, -1.57262, 6.81934, 5.00406, 12.27251, 5.00406, 12.02231, 5.00404, 11.77209, -0.77997, 5.25011, -2.0E-5, 0.21759, -1.16446, -4.57847, 0.83398, -11.73596, 0.83399, -11.73596, 0.83398, -11.73596, 0, -5.27904, 0, 0.21761, -1.45307, 5.50713, -0.834, 11.35709, -0.834, 11.35709, -0.83398, 11.35709, -1.56, 4.78606, 0, 0.21762, -1.16415, -3.98456, 7.50604, -8.58884, 7.50604, -8.58884, 7.50604, -8.58884, 0, -5.02885, 0, 0.21761, -1.55815, 5.23581, -1.66797, 11.1248, -1.66797, 11.20821, -1.66797, 11.2916, 4.67993, 5.88948, 0, 0.77354, -1.4995, -4.78566, 1.66809, -13.26294, 1.66809, -13.51314, 1.66809, -13.76334, 0, -9.68678, 0, -0.89429, -2.98834, 7.29605, 1.66809, 19.13873, 1.66809, 19.38901, 1.66809, 19.63927, 2.33997, 5.55582, 0, 0.77354, -1.77172, -4.10361, 1.66797, -6.79477, 1.66797, -7.17917, 1.66797, -7.51561 ]
						},
						{
							"time": 14.1667,
							"vertices": [ 5.4423, 36.74341, 2.50208, 22.4073, -0.61792, 8.74612, -20.43298, 10.69128, -20.43298, 10.40019, -20.43298, 10.10912, -0.83398, 21.86665, -0.83398, 21.47856, -0.83398, 21.09045, 2.99615, 13.43097, 0.83405, 8.38094, 0.83405, 3.0188, 1.66815, -2.03229, 1.66815, -2.12936, 1.66815, -2.22639, 6.66983, 0.0624, 2.91913, 5.67944, 2.13916, 11.91512, 3.33594, 19.28203, 3.33594, 19.37907, 3.33594, 19.4761, 7.76163, 12.1587, 3.75311, 5.68289, 2.19318, -1.28064, -4.17004, -4.60562, -4.17004, -4.7997, -4.17004, -4.99379, 7.08997, 0.92159, 5.42105, 4.72644, 6.20103, 8.8512, 0.83398, 14.2666, 0.83398, 14.16959, 0.83398, 14.07257, 0.83398, 8.49553, 0.83398, 4.07968, -0.6343, -0.16684, -1.66798, -7.2715, -1.66798, -7.07747, -1.66798, -6.88342, 1.41875, 1.68527, 0, 5.71057, -0.77997, 9.811, 0, 13.49513, 3.0E-5, 13.49513, 0, 13.49513, 6.78014, 8.50565, 8.3401, 5.03604, 7.41383, 1.80254, 0.83398, -4.61966, 0.83398, -4.71669, 0.83398, -4.81372, -0.98257, -0.20425, -2.50195, 4.22059, -3.28192, 8.73347, -7.50604, 15.34781, -7.50604, 15.15372, -7.50604, 14.95964, 2.1944, 5.99016, 0.83411, 1.40926, 6.29395, -3.92856, 3.33606, -7.8446, 3.33606, -7.35939, 3.33606, -6.87418, 5.06127, 5.21918, 3.75305, 9.87093, 2.97302, 14.57796, 0.83398, 16.98309, 0.83398, 17.17726, 0.83398, 17.37141, -0.41711, 10.09419, -0.41711, 9.64694, -0.41711, 9.25549 ]
						},
						{
							"time": 15,
							"offset": 1,
							"vertices": [ 8.00562, 0, 4.90302, 0, 1.93633, -17.51404, -5.80888, -17.51404, -6.03127, -17.51404, -6.25365, 3.26176, -4.11502, 0, 3.42049, -3.19983, 10.97141, 1.66809, 22.42999, 1.66809, 22.42999, 1.66809, 22.42999, 0, 10.47008, 0, 3.42049, -2.03263, -3.24004, 3.33612, -8.89403, 3.33612, -9.19054, 3.33612, -9.48705, 1.84326, -3.427, 0, 2.84715, 0, 9.46077, 4.1701, 15.84467, 4.1701, 16.06705, 4.1701, 16.28943, 0, 7.87022, 0, 2.92633, -0.91694, -1.90519, 5.83804, -9.69621, 5.83804, -9.91861, 5.83804, -10.14102, 1.2971, -3.84834, 0, 1.44379, 0.79999, 7.03725, 0.83399, 15.49356, 0.83399, 15.49356, 0.83399, 15.49356, 3.19992, 6.09119, 0, 1.4438, -1.30503, -3.48846, 0.83398, -7.15193, 0.83398, -7.15193, 0.83398, -7.15193, 1.4164, -3.72123, 0, 1.44382, 1.59998, 7.11139, 9.17416, 13.30038, 9.17416, 13.30038, 9.17416, 13.30038, 0.79999, 7.1855, 0, 1.4438, -1.39837, -4.2055, -3.33594, -10.44722, -3.33594, -10.37309, -3.33594, -10.29897, 2.3999, -4.01729, 0, 1.93797, -1.79736, 7.9965, 1.2E-4, 11.13127, 1.2E-4, 10.90887, 1.2E-4, 10.68648, 2.40002, 5.31636, 0, 0.45546, -1.4585, -4.54912, 5.83801, -6.38606, 5.83801, -6.16362, 5.83801, -5.94115, 0, -4.74986, 0, 1.93799, -1.89124, 8.26043, -2.5022, 21.9817, -2.5022, 21.64, -2.5022, 21.34094 ]
						},
						{
							"time": 15.8333,
							"vertices": [ 1.66797, 31.62943, 1.66797, 22.19772, 1.66797, 13.17914, -18.55323, 15.52565, -20.43298, 10.12985, -18.03296, 4.24096, -1.66797, -6.66167, -1.66797, -7.56302, -1.66797, -8.46437, 4.83405, -2.40634, 0.83411, 1.57994, -0.86956, 5.84239, 5.00397, 17.27699, 5.00397, 17.05159, 5.00397, 16.82617, 4.74113, 7.88489, 2.91919, 3.02635, 1.31915, -1.86133, 0, -2.17888, 0, -1.95351, 0, -1.72815, 4.55316, -0.52504, 3.75311, 4.1373, 2.26116, 8.72395, 0, 16.00009, 0, 15.54935, 0, 15.09859, 9.07128, 7.22823, 5.42105, 0.81306, 5.42105, -6.30243, 2.50211, -9.83041, 2.50211, -10.05574, 2.50211, -10.28105, 3.252, -5.8217, 0.83398, -0.68913, -3.16595, 4.21708, 2.50195, 10.5919, 2.50195, 11.04256, 2.50195, 11.49323, 1.63978, 6.09105, 0, 1.9957, 0, -2.29723, 3.33606, -7.49828, 3.33606, -7.49828, 3.33606, -7.49828, 9.79077, -1.18593, 8.3401, 2.63506, 8.34004, 6.62136, 0.83398, 9.03021, 0.83405, 8.80487, 0.83398, 8.57951, -0.92737, 5.24058, -2.50195, 1.29264, -5.7019, -2.46833, -0.83398, -5.86497, -0.83392, -6.31572, -0.83398, -6.76648, 2.43408, -4.50352, 0.83411, -0.27337, -1.1548, 3.90665, 0, 6.59148, 0, 7.71838, 0, 8.84528, 7.75293, 8.35286, 3.75305, 2.28308, -0.02545, -3.82588, -0.83398, -10.60266, -0.83398, -10.15175, -0.83398, -9.70084, 1.18286, 1.93874, -0.41711, 6.72612, -3.25034, 10.6385 ]
						},
						{
							"time": 16.6667,
							"vertices": [ 1.53552, 3.94153, 0, 4.10921, 0.78003, 4.5787, -23.35193, 18.57678, -23.35193, 18.3266, -23.35193, 18.07642, 0, 8.10477, 0, 2.44136, -1.36955, -3.03225, 0, -9.25406, 6.0E-5, -9.25406, 0, -9.25406, -0.78003, -2.80507, 0, 2.44136, -1.53129, 7.34765, 2.50214, 13.17496, 2.50214, 12.84138, 2.50214, 12.5078, -1.56018, 6.66209, 0, 1.79637, -1.31093, -2.67476, 3.33612, -10.31834, 3.33612, -10.06816, 3.33609, -9.81798, 0, -3.27762, 0, 1.88542, -1.57262, 6.81934, 5.00406, 12.27251, 5.00406, 12.02231, 5.00404, 11.77209, -0.77997, 5.25011, -2.0E-5, 0.21759, -1.16446, -4.57847, 0.83398, -11.73596, 0.83399, -11.73596, 0.83398, -11.73596, 0, -5.27904, 0, 0.21761, -1.45307, 5.50713, -0.834, 11.35709, -0.834, 11.35709, -0.83398, 11.35709, -1.56, 4.78606, 0, 0.21762, -1.16415, -3.98456, 7.50604, -8.58884, 7.50604, -8.58884, 7.50604, -8.58884, 0, -5.02885, 0, 0.21761, -1.55815, 5.23581, -1.66797, 11.1248, -1.66797, 11.20821, -1.66797, 11.2916, 4.67993, 5.88948, 0, 0.77354, -1.4995, -4.78566, 1.66809, -13.26294, 1.66809, -13.51314, 1.66809, -13.76334, 0, -9.68678, 0, -0.89429, -2.98834, 7.29605, 1.66809, 19.13873, 1.66809, 19.38901, 1.66809, 19.63927, 2.33997, 5.55582, 0, 0.77354, -1.77172, -4.10361, 1.66797, -6.79477, 1.66797, -7.17917, 1.66797, -7.51561 ]
						},
						{
							"time": 17.5,
							"vertices": [ 5.4423, 36.74341, 2.50208, 22.4073, -0.61792, 8.74612, -20.43298, 10.69128, -20.43298, 10.40019, -20.43298, 10.10912, -0.83398, 21.86665, -0.83398, 21.47856, -0.83398, 21.09045, 2.99615, 13.43097, 0.83405, 8.38094, 0.83405, 3.0188, 1.66815, -2.03229, 1.66815, -2.12936, 1.66815, -2.22639, 6.66983, 0.0624, 2.91913, 5.67944, 2.13916, 11.91512, 3.33594, 19.28203, 3.33594, 19.37907, 3.33594, 19.4761, 7.76163, 12.1587, 3.75311, 5.68289, 2.19318, -1.28064, -4.17004, -4.60562, -4.17004, -4.7997, -4.17004, -4.99379, 7.08997, 0.92159, 5.42105, 4.72644, 6.20103, 8.8512, 0.83398, 14.2666, 0.83398, 14.16959, 0.83398, 14.07257, 0.83398, 8.49553, 0.83398, 4.07968, -0.6343, -0.16684, -1.66798, -7.2715, -1.66798, -7.07747, -1.66798, -6.88342, 1.41875, 1.68527, 0, 5.71057, -0.77997, 9.811, 0, 13.49513, 3.0E-5, 13.49513, 0, 13.49513, 6.78014, 8.50565, 8.3401, 5.03604, 7.41383, 1.80254, 0.83398, -4.61966, 0.83398, -4.71669, 0.83398, -4.81372, -0.98257, -0.20425, -2.50195, 4.22059, -3.28192, 8.73347, -7.50604, 15.34781, -7.50604, 15.15372, -7.50604, 14.95964, 2.1944, 5.99016, 0.83411, 1.40926, 6.29395, -3.92856, 3.33606, -7.8446, 3.33606, -7.35939, 3.33606, -6.87418, 5.06127, 5.21918, 3.75305, 9.87093, 2.97302, 14.57796, 0.83398, 16.98309, 0.83398, 17.17726, 0.83398, 17.37141, -0.41711, 10.09419, -0.41711, 9.64694, -0.41711, 9.25549 ]
						},
						{
							"time": 18.3333,
							"offset": 1,
							"vertices": [ 8.00562, 0, 4.90302, 0, 1.93633, -17.51404, -5.80888, -17.51404, -6.03127, -17.51404, -6.25365, 3.26176, -4.11502, 0, 3.42049, -3.19983, 10.97141, 1.66809, 22.42999, 1.66809, 22.42999, 1.66809, 22.42999, 0, 10.47008, 0, 3.42049, -2.03263, -3.24004, 3.33612, -8.89403, 3.33612, -9.19054, 3.33612, -9.48705, 1.84326, -3.427, 0, 2.84715, 0, 9.46077, 4.1701, 15.84467, 4.1701, 16.06705, 4.1701, 16.28943, 0, 7.87022, 0, 2.92633, -0.91694, -1.90519, 5.83804, -9.69621, 5.83804, -9.91861, 5.83804, -10.14102, 1.2971, -3.84834, 0, 1.44379, 0.79999, 7.03725, 0.83399, 15.49356, 0.83399, 15.49356, 0.83399, 15.49356, 3.19992, 6.09119, 0, 1.4438, -1.30503, -3.48846, 0.83398, -7.15193, 0.83398, -7.15193, 0.83398, -7.15193, 1.4164, -3.72123, 0, 1.44382, 1.59998, 7.11139, 9.17416, 13.30038, 9.17416, 13.30038, 9.17416, 13.30038, 0.79999, 7.1855, 0, 1.4438, -1.39837, -4.2055, -3.33594, -10.44722, -3.33594, -10.37309, -3.33594, -10.29897, 2.3999, -4.01729, 0, 1.93797, -1.79736, 7.9965, 1.2E-4, 11.13127, 1.2E-4, 10.90887, 1.2E-4, 10.68648, 2.40002, 5.31636, 0, 0.45546, -1.4585, -4.54912, 5.83801, -6.38606, 5.83801, -6.16362, 5.83801, -5.94115, 0, -4.74986, 0, 1.93799, -1.89124, 8.26043, -2.5022, 21.9817, -2.5022, 21.64, -2.5022, 21.34094 ]
						},
						{
							"time": 19.1667,
							"vertices": [ 1.66797, 31.62943, 1.66797, 22.19772, 1.66797, 13.17914, -18.55323, 15.52565, -20.43298, 10.12985, -18.03296, 4.24096, -1.66797, -6.66167, -1.66797, -7.56302, -1.66797, -8.46437, 4.83405, -2.40634, 0.83411, 1.57994, -0.86956, 5.84239, 5.00397, 17.27699, 5.00397, 17.05159, 5.00397, 16.82617, 4.74113, 7.88489, 2.91919, 3.02635, 1.31915, -1.86133, 0, -2.17888, 0, -1.95351, 0, -1.72815, 4.55316, -0.52504, 3.75311, 4.1373, 2.26116, 8.72395, 0, 16.00009, 0, 15.54935, 0, 15.09859, 9.07128, 7.22823, 5.42105, 0.81306, 5.42105, -6.30243, 2.50211, -9.83041, 2.50211, -10.05574, 2.50211, -10.28105, 3.252, -5.8217, 0.83398, -0.68913, -3.16595, 4.21708, 2.50195, 10.5919, 2.50195, 11.04256, 2.50195, 11.49323, 1.63978, 6.09105, 0, 1.9957, 0, -2.29723, 3.33606, -7.49828, 3.33606, -7.49828, 3.33606, -7.49828, 9.79077, -1.18593, 8.3401, 2.63506, 8.34004, 6.62136, 0.83398, 9.03021, 0.83405, 8.80487, 0.83398, 8.57951, -0.92737, 5.24058, -2.50195, 1.29264, -5.7019, -2.46833, -0.83398, -5.86497, -0.83392, -6.31572, -0.83398, -6.76648, 2.43408, -4.50352, 0.83411, -0.27337, -1.1548, 3.90665, 0, 6.59148, 0, 7.71838, 0, 8.84528, 7.75293, 8.35286, 3.75305, 2.28308, -0.02545, -3.82588, -0.83398, -10.60266, -0.83398, -10.15175, -0.83398, -9.70084, 1.18286, 1.93874, -0.41711, 6.72612, -3.25034, 10.6385 ]
						},
						{
							"time": 20,
							"vertices": [ 1.53552, 3.94153, 0, 4.10921, 0.78003, 4.5787, -23.35193, 18.57678, -23.35193, 18.3266, -23.35193, 18.07642, 0, 8.10477, 0, 2.44136, -1.36955, -3.03225, 0, -9.25406, 6.0E-5, -9.25406, 0, -9.25406, -0.78003, -2.80507, 0, 2.44136, -1.53129, 7.34765, 2.50214, 13.17496, 2.50214, 12.84138, 2.50214, 12.5078, -1.56018, 6.66209, 0, 1.79637, -1.31093, -2.67476, 3.33612, -10.31834, 3.33612, -10.06816, 3.33609, -9.81798, 0, -3.27762, 0, 1.88542, -1.57262, 6.81934, 5.00406, 12.27251, 5.00406, 12.02231, 5.00404, 11.77209, -0.77997, 5.25011, -2.0E-5, 0.21759, -1.16446, -4.57847, 0.83398, -11.73596, 0.83399, -11.73596, 0.83398, -11.73596, 0, -5.27904, 0, 0.21761, -1.45307, 5.50713, -0.834, 11.35709, -0.834, 11.35709, -0.83398, 11.35709, -1.56, 4.78606, 0, 0.21762, -1.16415, -3.98456, 7.50604, -8.58884, 7.50604, -8.58884, 7.50604, -8.58884, 0, -5.02885, 0, 0.21761, -1.55815, 5.23581, -1.66797, 11.1248, -1.66797, 11.20821, -1.66797, 11.2916, 4.67993, 5.88948, 0, 0.77354, -1.4995, -4.78566, 1.66809, -13.26294, 1.66809, -13.51314, 1.66809, -13.76334, 0, -9.68678, 0, -0.89429, -2.98834, 7.29605, 1.66809, 19.13873, 1.66809, 19.38901, 1.66809, 19.63927, 2.33997, 5.55582, 0, 0.77354, -1.77172, -4.10361, 1.66797, -6.79477, 1.66797, -7.17917, 1.66797, -7.51561 ]
						},
						{
							"time": 20.8333,
							"vertices": [ 5.4423, 36.74341, 2.50208, 22.4073, -0.61792, 8.74612, -20.43298, 10.69128, -20.43298, 10.40019, -20.43298, 10.10912, -0.83398, 21.86665, -0.83398, 21.47856, -0.83398, 21.09045, 2.99615, 13.43097, 0.83405, 8.38094, 0.83405, 3.0188, 1.66815, -2.03229, 1.66815, -2.12936, 1.66815, -2.22639, 6.66983, 0.0624, 2.91913, 5.67944, 2.13916, 11.91512, 3.33594, 19.28203, 3.33594, 19.37907, 3.33594, 19.4761, 7.76163, 12.1587, 3.75311, 5.68289, 2.19318, -1.28064, -4.17004, -4.60562, -4.17004, -4.7997, -4.17004, -4.99379, 7.08997, 0.92159, 5.42105, 4.72644, 6.20103, 8.8512, 0.83398, 14.2666, 0.83398, 14.16959, 0.83398, 14.07257, 0.83398, 8.49553, 0.83398, 4.07968, -0.6343, -0.16684, -1.66798, -7.2715, -1.66798, -7.07747, -1.66798, -6.88342, 1.41875, 1.68527, 0, 5.71057, -0.77997, 9.811, 0, 13.49513, 3.0E-5, 13.49513, 0, 13.49513, 6.78014, 8.50565, 8.3401, 5.03604, 7.41383, 1.80254, 0.83398, -4.61966, 0.83398, -4.71669, 0.83398, -4.81372, -0.98257, -0.20425, -2.50195, 4.22059, -3.28192, 8.73347, -7.50604, 15.34781, -7.50604, 15.15372, -7.50604, 14.95964, 2.1944, 5.99016, 0.83411, 1.40926, 6.29395, -3.92856, 3.33606, -7.8446, 3.33606, -7.35939, 3.33606, -6.87418, 5.06127, 5.21918, 3.75305, 9.87093, 2.97302, 14.57796, 0.83398, 16.98309, 0.83398, 17.17726, 0.83398, 17.37141, -0.41711, 10.09419, -0.41711, 9.64694, -0.41711, 9.25549 ]
						},
						{
							"time": 21.6667,
							"offset": 1,
							"vertices": [ 8.00562, 0, 4.90302, 0, 1.93633, -17.51404, -5.80888, -17.51404, -6.03127, -17.51404, -6.25365, 3.26176, -4.11502, 0, 3.42049, -3.19983, 10.97141, 1.66809, 22.42999, 1.66809, 22.42999, 1.66809, 22.42999, 0, 10.47008, 0, 3.42049, -2.03263, -3.24004, 3.33612, -8.89403, 3.33612, -9.19054, 3.33612, -9.48705, 1.84326, -3.427, 0, 2.84715, 0, 9.46077, 4.1701, 15.84467, 4.1701, 16.06705, 4.1701, 16.28943, 0, 7.87022, 0, 2.92633, -0.91694, -1.90519, 5.83804, -9.69621, 5.83804, -9.91861, 5.83804, -10.14102, 1.2971, -3.84834, 0, 1.44379, 0.79999, 7.03725, 0.83399, 15.49356, 0.83399, 15.49356, 0.83399, 15.49356, 3.19992, 6.09119, 0, 1.4438, -1.30503, -3.48846, 0.83398, -7.15193, 0.83398, -7.15193, 0.83398, -7.15193, 1.4164, -3.72123, 0, 1.44382, 1.59998, 7.11139, 9.17416, 13.30038, 9.17416, 13.30038, 9.17416, 13.30038, 0.79999, 7.1855, 0, 1.4438, -1.39837, -4.2055, -3.33594, -10.44722, -3.33594, -10.37309, -3.33594, -10.29897, 2.3999, -4.01729, 0, 1.93797, -1.79736, 7.9965, 1.2E-4, 11.13127, 1.2E-4, 10.90887, 1.2E-4, 10.68648, 2.40002, 5.31636, 0, 0.45546, -1.4585, -4.54912, 5.83801, -6.38606, 5.83801, -6.16362, 5.83801, -5.94115, 0, -4.74986, 0, 1.93799, -1.89124, 8.26043, -2.5022, 21.9817, -2.5022, 21.64, -2.5022, 21.34094 ]
						},
						{
							"time": 22.5,
							"vertices": [ 1.66797, 31.62943, 1.66797, 22.19772, 1.66797, 13.17914, -18.55323, 15.52565, -20.43298, 10.12985, -18.03296, 4.24096, -1.66797, -6.66167, -1.66797, -7.56302, -1.66797, -8.46437, 4.83405, -2.40634, 0.83411, 1.57994, -0.86956, 5.84239, 5.00397, 17.27699, 5.00397, 17.05159, 5.00397, 16.82617, 4.74113, 7.88489, 2.91919, 3.02635, 1.31915, -1.86133, 0, -2.17888, 0, -1.95351, 0, -1.72815, 4.55316, -0.52504, 3.75311, 4.1373, 2.26116, 8.72395, 0, 16.00009, 0, 15.54935, 0, 15.09859, 9.07128, 7.22823, 5.42105, 0.81306, 5.42105, -6.30243, 2.50211, -9.83041, 2.50211, -10.05574, 2.50211, -10.28105, 3.252, -5.8217, 0.83398, -0.68913, -3.16595, 4.21708, 2.50195, 10.5919, 2.50195, 11.04256, 2.50195, 11.49323, 1.63978, 6.09105, 0, 1.9957, 0, -2.29723, 3.33606, -7.49828, 3.33606, -7.49828, 3.33606, -7.49828, 9.79077, -1.18593, 8.3401, 2.63506, 8.34004, 6.62136, 0.83398, 9.03021, 0.83405, 8.80487, 0.83398, 8.57951, -0.92737, 5.24058, -2.50195, 1.29264, -5.7019, -2.46833, -0.83398, -5.86497, -0.83392, -6.31572, -0.83398, -6.76648, 2.43408, -4.50352, 0.83411, -0.27337, -1.1548, 3.90665, 0, 6.59148, 0, 7.71838, 0, 8.84528, 7.75293, 8.35286, 3.75305, 2.28308, -0.02545, -3.82588, -0.83398, -10.60266, -0.83398, -10.15175, -0.83398, -9.70084, 1.18286, 1.93874, -0.41711, 6.72612, -3.25034, 10.6385 ]
						},
						{
							"time": 23.3333,
							"vertices": [ 1.53552, 3.94153, 0, 4.10921, 0.78003, 4.5787, -23.35193, 18.57678, -23.35193, 18.3266, -23.35193, 18.07642, 0, 8.10477, 0, 2.44136, -1.36955, -3.03225, 0, -9.25406, 6.0E-5, -9.25406, 0, -9.25406, -0.78003, -2.80507, 0, 2.44136, -1.53129, 7.34765, 2.50214, 13.17496, 2.50214, 12.84138, 2.50214, 12.5078, -1.56018, 6.66209, 0, 1.79637, -1.31093, -2.67476, 3.33612, -10.31834, 3.33612, -10.06816, 3.33609, -9.81798, 0, -3.27762, 0, 1.88542, -1.57262, 6.81934, 5.00406, 12.27251, 5.00406, 12.02231, 5.00404, 11.77209, -0.77997, 5.25011, -2.0E-5, 0.21759, -1.16446, -4.57847, 0.83398, -11.73596, 0.83399, -11.73596, 0.83398, -11.73596, 0, -5.27904, 0, 0.21761, -1.45307, 5.50713, -0.834, 11.35709, -0.834, 11.35709, -0.83398, 11.35709, -1.56, 4.78606, 0, 0.21762, -1.16415, -3.98456, 7.50604, -8.58884, 7.50604, -8.58884, 7.50604, -8.58884, 0, -5.02885, 0, 0.21761, -1.55815, 5.23581, -1.66797, 11.1248, -1.66797, 11.20821, -1.66797, 11.2916, 4.67993, 5.88948, 0, 0.77354, -1.4995, -4.78566, 1.66809, -13.26294, 1.66809, -13.51314, 1.66809, -13.76334, 0, -9.68678, 0, -0.89429, -2.98834, 7.29605, 1.66809, 19.13873, 1.66809, 19.38901, 1.66809, 19.63927, 2.33997, 5.55582, 0, 0.77354, -1.77172, -4.10361, 1.66797, -6.79477, 1.66797, -7.17917, 1.66797, -7.51561 ]
						},
						{
							"time": 24.1667,
							"vertices": [ 5.4423, 36.74341, 2.50208, 22.4073, -0.61792, 8.74612, -20.43298, 10.69128, -20.43298, 10.40019, -20.43298, 10.10912, -0.83398, 21.86665, -0.83398, 21.47856, -0.83398, 21.09045, 2.99615, 13.43097, 0.83405, 8.38094, 0.83405, 3.0188, 1.66815, -2.03229, 1.66815, -2.12936, 1.66815, -2.22639, 6.66983, 0.0624, 2.91913, 5.67944, 2.13916, 11.91512, 3.33594, 19.28203, 3.33594, 19.37907, 3.33594, 19.4761, 7.76163, 12.1587, 3.75311, 5.68289, 2.19318, -1.28064, -4.17004, -4.60562, -4.17004, -4.7997, -4.17004, -4.99379, 7.08997, 0.92159, 5.42105, 4.72644, 6.20103, 8.8512, 0.83398, 14.2666, 0.83398, 14.16959, 0.83398, 14.07257, 0.83398, 8.49553, 0.83398, 4.07968, -0.6343, -0.16684, -1.66798, -7.2715, -1.66798, -7.07747, -1.66798, -6.88342, 1.41875, 1.68527, 0, 5.71057, -0.77997, 9.811, 0, 13.49513, 3.0E-5, 13.49513, 0, 13.49513, 6.78014, 8.50565, 8.3401, 5.03604, 7.41383, 1.80254, 0.83398, -4.61966, 0.83398, -4.71669, 0.83398, -4.81372, -0.98257, -0.20425, -2.50195, 4.22059, -3.28192, 8.73347, -7.50604, 15.34781, -7.50604, 15.15372, -7.50604, 14.95964, 2.1944, 5.99016, 0.83411, 1.40926, 6.29395, -3.92856, 3.33606, -7.8446, 3.33606, -7.35939, 3.33606, -6.87418, 5.06127, 5.21918, 3.75305, 9.87093, 2.97302, 14.57796, 0.83398, 16.98309, 0.83398, 17.17726, 0.83398, 17.37141, -0.41711, 10.09419, -0.41711, 9.64694, -0.41711, 9.25549 ]
						},
						{
							"time": 25,
							"offset": 1,
							"vertices": [ 8.00562, 0, 4.90302, 0, 1.93633, -17.51404, -5.80888, -17.51404, -6.03127, -17.51404, -6.25365, 3.26176, -4.11502, 0, 3.42049, -3.19983, 10.97141, 1.66809, 22.42999, 1.66809, 22.42999, 1.66809, 22.42999, 0, 10.47008, 0, 3.42049, -2.03263, -3.24004, 3.33612, -8.89403, 3.33612, -9.19054, 3.33612, -9.48705, 1.84326, -3.427, 0, 2.84715, 0, 9.46077, 4.1701, 15.84467, 4.1701, 16.06705, 4.1701, 16.28943, 0, 7.87022, 0, 2.92633, -0.91694, -1.90519, 5.83804, -9.69621, 5.83804, -9.91861, 5.83804, -10.14102, 1.2971, -3.84834, 0, 1.44379, 0.79999, 7.03725, 0.83399, 15.49356, 0.83399, 15.49356, 0.83399, 15.49356, 3.19992, 6.09119, 0, 1.4438, -1.30503, -3.48846, 0.83398, -7.15193, 0.83398, -7.15193, 0.83398, -7.15193, 1.4164, -3.72123, 0, 1.44382, 1.59998, 7.11139, 9.17416, 13.30038, 9.17416, 13.30038, 9.17416, 13.30038, 0.79999, 7.1855, 0, 1.4438, -1.39837, -4.2055, -3.33594, -10.44722, -3.33594, -10.37309, -3.33594, -10.29897, 2.3999, -4.01729, 0, 1.93797, -1.79736, 7.9965, 1.2E-4, 11.13127, 1.2E-4, 10.90887, 1.2E-4, 10.68648, 2.40002, 5.31636, 0, 0.45546, -1.4585, -4.54912, 5.83801, -6.38606, 5.83801, -6.16362, 5.83801, -5.94115, 0, -4.74986, 0, 1.93799, -1.89124, 8.26043, -2.5022, 21.9817, -2.5022, 21.64, -2.5022, 21.34094 ]
						},
						{
							"time": 25.8333,
							"vertices": [ 1.66797, 31.62943, 1.66797, 22.19772, 1.66797, 13.17914, -18.55323, 15.52565, -20.43298, 10.12985, -18.03296, 4.24096, -1.66797, -6.66167, -1.66797, -7.56302, -1.66797, -8.46437, 4.83405, -2.40634, 0.83411, 1.57994, -0.86956, 5.84239, 5.00397, 17.27699, 5.00397, 17.05159, 5.00397, 16.82617, 4.74113, 7.88489, 2.91919, 3.02635, 1.31915, -1.86133, 0, -2.17888, 0, -1.95351, 0, -1.72815, 4.55316, -0.52504, 3.75311, 4.1373, 2.26116, 8.72395, 0, 16.00009, 0, 15.54935, 0, 15.09859, 9.07128, 7.22823, 5.42105, 0.81306, 5.42105, -6.30243, 2.50211, -9.83041, 2.50211, -10.05574, 2.50211, -10.28105, 3.252, -5.8217, 0.83398, -0.68913, -3.16595, 4.21708, 2.50195, 10.5919, 2.50195, 11.04256, 2.50195, 11.49323, 1.63978, 6.09105, 0, 1.9957, 0, -2.29723, 3.33606, -7.49828, 3.33606, -7.49828, 3.33606, -7.49828, 9.79077, -1.18593, 8.3401, 2.63506, 8.34004, 6.62136, 0.83398, 9.03021, 0.83405, 8.80487, 0.83398, 8.57951, -0.92737, 5.24058, -2.50195, 1.29264, -5.7019, -2.46833, -0.83398, -5.86497, -0.83392, -6.31572, -0.83398, -6.76648, 2.43408, -4.50352, 0.83411, -0.27337, -1.1548, 3.90665, 0, 6.59148, 0, 7.71838, 0, 8.84528, 7.75293, 8.35286, 3.75305, 2.28308, -0.02545, -3.82588, -0.83398, -10.60266, -0.83398, -10.15175, -0.83398, -9.70084, 1.18286, 1.93874, -0.41711, 6.72612, -3.25034, 10.6385 ]
						},
						{
							"time": 26.6667,
							"vertices": [ 1.53552, 3.94153, 0, 4.10921, 0.78003, 4.5787, -23.35193, 18.57678, -23.35193, 18.3266, -23.35193, 18.07642, 0, 8.10477, 0, 2.44136, -1.36955, -3.03225, 0, -9.25406, 6.0E-5, -9.25406, 0, -9.25406, -0.78003, -2.80507, 0, 2.44136, -1.53129, 7.34765, 2.50214, 13.17496, 2.50214, 12.84138, 2.50214, 12.5078, -1.56018, 6.66209, 0, 1.79637, -1.31093, -2.67476, 3.33612, -10.31834, 3.33612, -10.06816, 3.33609, -9.81798, 0, -3.27762, 0, 1.88542, -1.57262, 6.81934, 5.00406, 12.27251, 5.00406, 12.02231, 5.00404, 11.77209, -0.77997, 5.25011, -2.0E-5, 0.21759, -1.16446, -4.57847, 0.83398, -11.73596, 0.83399, -11.73596, 0.83398, -11.73596, 0, -5.27904, 0, 0.21761, -1.45307, 5.50713, -0.834, 11.35709, -0.834, 11.35709, -0.83398, 11.35709, -1.56, 4.78606, 0, 0.21762, -1.16415, -3.98456, 7.50604, -8.58884, 7.50604, -8.58884, 7.50604, -8.58884, 0, -5.02885, 0, 0.21761, -1.55815, 5.23581, -1.66797, 11.1248, -1.66797, 11.20821, -1.66797, 11.2916, 4.67993, 5.88948, 0, 0.77354, -1.4995, -4.78566, 1.66809, -13.26294, 1.66809, -13.51314, 1.66809, -13.76334, 0, -9.68678, 0, -0.89429, -2.98834, 7.29605, 1.66809, 19.13873, 1.66809, 19.38901, 1.66809, 19.63927, 2.33997, 5.55582, 0, 0.77354, -1.77172, -4.10361, 1.66797, -6.79477, 1.66797, -7.17917, 1.66797, -7.51561 ]
						}
					]
				}
			}
		}
	}
}
}